cov3rt/TestCloak.py
cov3rt/__init__.py
cov3rt/__main__.py
cov3rt/command_line.py
cov3rt/Cloaks/Cloak.py
cov3rt/Cloaks/DNSCaseModulation.py
cov3rt/Cloaks/DNSTiming.py
cov3rt/Cloaks/ICMPEchoMultiPayload.py
cov3rt/Cloaks/IPID.py
cov3rt/Cloaks/IPMorse.py
cov3rt/Cloaks/IPReservedBit.py
cov3rt/Cloaks/IPv6Hoppers.py
cov3rt/Cloaks/TCPFourCharPatsySeqNum.py
cov3rt/Cloaks/TCPOneCharSeqNum.py
cov3rt/Cloaks/UDPChecksum.py
cov3rt/Cloaks/UDPFlood.py
cov3rt/Cloaks/UDPSizeModulation.py
cov3rt/Cloaks/__init__.py
cov3rt/Tools/ReverseShellAttacker.py
cov3rt/Tools/ReverseShellVictim.py
cov3rt/Tools/__init__.py
cov3rt/Tools/teamCommunication.py
cov3rt/UserCloaks/ICMPEchoFullPayload.py
cov3rt/UserCloaks/__init__.py
cov3rt-1.0.dist-info/LICENSE
cov3rt-1.0.dist-info/METADATA
cov3rt-1.0.dist-info/WHEEL
cov3rt-1.0.dist-info/entry_points.txt
cov3rt-1.0.dist-info/top_level.txt
cov3rt-1.0.dist-info/RECORD
