Metadata-Version: 2.1
Name: cov3rt
Version: 1.0
Summary: Covert Channel Management, Integration, and Implementation
Home-page: https://github.com/jbert1/Cov3rt/
Author: Justin Berthelot Sam Dominguez Daniel Munger Christopher Rice
Author-email: pythoncov3rt@gmail.com
License: GPLv2
Project-URL: Documentation, https://github.com/jbert1/Cov3rt/blob/main/cov3rt-documentation.md
Project-URL: Source Code, https://github.com/jbert1/Cov3rt/
Platform: UNKNOWN
Requires-Python: >=3.6.0
Requires-Dist: psutil (>=5.6.0)
Requires-Dist: scapy (>=2.4.0)
Requires-Dist: npyscreen (>=4.9)
Requires-Dist: windows-curses (>=1.0) ; platform_system == "Windows"
